README.md
setup.py
method_cache.egg-info/PKG-INFO
method_cache.egg-info/SOURCES.txt
method_cache.egg-info/dependency_links.txt
method_cache.egg-info/top_level.txt
methodcache/__init__.py
methodcache/cache.py
methodcache/exceptions.py
methodcache/helper.py
methodcache/store.py