Metadata-Version: 2.1
Name: method-cache
Version: 0.0.3
Summary: Simple TTL Cache for methods and there results.
Home-page: https://github.com/eieste/MethodCache
Author: Stefan Eiermann
Author-email: python-org@ultraapp.de
License: UNKNOWN
Platform: UNKNOWN
Classifier: Programming Language :: Python :: 3
Classifier: License :: OSI Approved :: MIT License
Classifier: Operating System :: OS Independent
Classifier: Topic :: Software Development
